[
  {"text": "Сделать отчёт сегодня","priority": "high"},
  {"text": "Пофиксить баг сегодня","priority": "high"},
  {"text": "Купить продукты завтра","priority": "high"},
  {"text": "Сходить в зал сегодня вечером","priority": "high"},
  {"text": "Сделать задачу срочно","priority": "high"},
  {"text": "Оплатить аренду до завтра","priority": "high"},
  {"text": "Сдать работу сегодня","priority": "high"},
  {"text": "Нужно срочно оплатить","priority": "high"},
  {"text": "Немедленно отправить письмо","priority": "high"},
  {"text": "Срочно сделать отчёт","priority": "high"},
  {"text": "Пофиксить баг до завтра","priority": "high"},
  {"text": "Закончить отчёт сегодня","priority": "high"},
  {"text": "Сделать презентацию сегодня","priority": "high"},
  {"text": "Сдать код сегодня","priority": "high"},
  {"text": "Сделать задачу прямо сейчас","priority": "high"},
  {"text": "Оплатить счёт сегодня","priority": "high"},
  {"text": "Отправить отчёт сегодня","priority": "high"},
  {"text": "Сходить в магазин сегодня","priority": "high"},
  {"text": "Закончить работу до завтра","priority": "high"},
  {"text": "Исправить баг срочно","priority": "high"},
  {"text": "Сделать отчёт в пятницу","today_weekday": 3,"priority": "high"},
  {"text": "Подготовить презентацию в пятницу","today_weekday": 3,"priority": "high"},
  {"text": "Отправить письмо клиенту в пятницу","today_weekday": 3,"priority": "high"},
  {"text": "Сделать отчёт в четверг","today_weekday": 2,"priority": "high"},
  {"text": "Подготовить презентацию в четверг","today_weekday": 2,"priority": "high"},
  {"text": "Сделать отчёт в пятницу","today_weekday": 0,"priority": "medium"},
  {"text": "Подготовить презентацию в пятницу","today_weekday": 2,"priority": "medium"},
  {"text": "Отправить письмо клиенту в пятницу","today_weekday": 1,"priority": "medium"},
  {"text": "Сделать отчёт в четверг","today_weekday": 0,"priority": "medium"},
  {"text": "Подготовить презентацию в четверг","today_weekday": 0,"priority": "medium"},
  {"text": "Закончить проект к пятнице","today_weekday": 2,"priority": "medium"},
  {"text": "Подготовить презентацию к пятнице","today_weekday": 1,"priority": "medium"},
  {"text": "Сделать отчёт на неделе","priority": "medium"},
  {"text": "Подготовить презентацию скоро","priority": "medium"},
  {"text": "Разобраться с проектом","priority": "medium"},
  {"text": "Написать код","priority": "medium"},
  {"text": "Проверить почту","priority": "medium"},
  {"text": "Начать проект когда-нибудь","priority": "low"},
  {"text": "Обновить документацию потом","priority": "low"},
  {"text": "Сделать анализ данных позже","priority": "low"},
  {"text": "Подготовить презентацию в будущем","priority": "low"},
  {"text": "Внести изменения в код когда будет время","priority": "low"},
  {"text": "Сделать домашнее задание потом","priority": "low"},
  {"text": "Обновить проектную документацию когда-нибудь","priority": "low"},
  {"text": "Составить план работы позже","priority": "low"},
  {"text": "Подготовить отчет в будущем","priority": "low"},
  {"text": "Сделать тестовое задание потом","priority": "low"},
  {"text": "Обновить графики когда будет время","priority": "low"},
  {"text": "Начать изучение нового инструмента позже","priority": "low"},
  {"text": "Внести исправления в проект когда-нибудь","priority": "low"},
  {"text": "Сделать черновик отчета позже","priority": "low"},
  {"text": "Подготовить план презентации в будущем","priority": "low"},
  {"text": "Обновить документацию команды потом","priority": "low"},
  {"text": "Начать работу с новым проектом когда-нибудь","priority": "low"},
  {"text": "Сделать домашку позже","priority": "low"},
  {"text": "Внести изменения в отчет когда будет время","priority": "low"},
  {"text": "Подготовить документы для совещания потом","priority": "low"},
  { "text": "Отправить отчёт сегодня", "priority": "high" },
  { "text": "Пофиксить баг сегодня", "priority": "high" },
  { "text": "Купить продукты завтра", "priority": "high" },
  { "text": "Сходить в зал сегодня вечером", "priority": "high" },
  { "text": "Сделать задачу срочно", "priority": "high" },
  { "text": "Оплатить аренду до завтра", "priority": "high" },
  { "text": "Сдать работу сегодня", "priority": "high" },
  { "text": "Нужно срочно оплатить", "priority": "high" },
  { "text": "Немедленно отправить письмо", "priority": "high" },
  { "text": "Срочно сделать отчёт", "priority": "high" },
  { "text": "Пофиксить баг до завтра", "priority": "high" },
  { "text": "Закончить отчёт сегодня", "priority": "high" },
  { "text": "Сделать презентацию сегодня", "priority": "high" },
  { "text": "Сдать код сегодня", "priority": "high" },
  { "text": "Сделать задачу прямо сейчас", "priority": "high" },
  { "text": "Оплатить счёт сегодня", "priority": "high" },
  { "text": "Отправить отчёт сегодня", "priority": "high" },
  { "text": "Сходить в магазин сегодня", "priority": "high" },
  { "text": "Закончить работу до завтра", "priority": "high" },
  { "text": "Исправить баг срочно", "priority": "high" },
  { "text": "Сделать отчёт в пятницу", "today_weekday": 3, "priority": "high" },
  { "text": "Подготовить презентацию в пятницу", "today_weekday": 3, "priority": "high" },
  { "text": "Отправить письмо клиенту в пятницу", "today_weekday": 3, "priority": "high" },
  { "text": "Сделать отчёт в четверг", "today_weekday": 2, "priority": "high" },
  { "text": "Подготовить презентацию в четверг", "today_weekday": 2, "priority": "high" },
  { "text": "Сделать отчёт в пятницу", "today_weekday": 0, "priority": "medium" },
  { "text": "Подготовить презентацию в пятницу", "today_weekday": 2, "priority": "medium" },
  { "text": "Отправить письмо клиенту в пятницу", "today_weekday": 1, "priority": "medium" },
  { "text": "Сделать отчёт в четверг", "today_weekday": 0, "priority": "medium" },
  { "text": "Подготовить презентацию в четверг", "today_weekday": 0, "priority": "medium" },
  { "text": "Закончить проект к пятнице", "today_weekday": 2, "priority": "medium" },
  { "text": "Подготовить презентацию к пятнице", "today_weekday": 1, "priority": "medium" },
  { "text": "Сделать отчёт на неделе", "priority": "medium" },
  { "text": "Подготовить презентацию скоро", "priority": "medium" },
  { "text": "Разобраться с проектом", "priority": "medium" },
  { "text": "Написать код", "priority": "medium" },
  { "text": "Проверить почту", "priority": "medium" },
  { "text": "Закончить проект до 1 мая", "priority": "medium" },
  { "text": "Обновить проект до конца недели", "priority": "medium" },
  { "text": "Закончить работу в следующем месяце", "priority": "medium" },
  { "text": "Заполнить форму до 10 числа", "priority": "medium" },
  { "text": "Подготовить отчёт на следующей неделе", "priority": "medium" },
  { "text": "Подготовить презентацию к 15 июня", "priority": "medium" },
  { "text": "Сделать обновление системы до 20 числа", "priority": "medium" },
  { "text": "Пофиксить баги до конца месяца", "priority": "medium" },
  { "text": "Провести анализ в следующем месяце", "priority": "medium" },
  { "text": "Начать проект когда-нибудь", "priority": "low" },
  { "text": "Обновить документацию потом", "priority": "low" },
  { "text": "Сделать анализ данных позже", "priority": "low" },
  { "text": "Подготовить презентацию в будущем", "priority": "low" },
  { "text": "Внести изменения в код когда будет время", "priority": "low" },
  { "text": "Сделать домашнее задание потом", "priority": "low" },
  { "text": "Обновить проектную документацию когда-нибудь", "priority": "low" },
  { "text": "Составить план работы позже", "priority": "low" },
  { "text": "Подготовить отчет в будущем", "priority": "low" },
  { "text": "Сделать тестовое задание потом", "priority": "low" },
  { "text": "Обновить графики когда будет время", "priority": "low" },
  { "text": "Начать изучение нового инструмента позже", "priority": "low" },
  { "text": "Внести исправления в проект когда-нибудь", "priority": "low" },
  { "text": "Сделать черновик отчета позже", "priority": "low" },
  { "text": "Подготовить план презентации в будущем", "priority": "low" },
  { "text": "Обновить документацию команды потом", "priority": "low" },
  { "text": "Начать работу с новым проектом когда-нибудь", "priority": "low" },
  { "text": "Сделать домашку позже", "priority": "low" },
  { "text": "Внести изменения в отчет когда будет время", "priority": "low" },
  { "text": "Подготовить документы для совещания потом", "priority": "low" }
]